CHANGES.rst
COPYRIGHT.rst
LICENSE.rst
MANIFEST.in
README.rst
buildout.cfg
setup.cfg
setup.py
src/buildout/__init__.py
src/buildout.environ.egg-info/PKG-INFO
src/buildout.environ.egg-info/SOURCES.txt
src/buildout.environ.egg-info/dependency_links.txt
src/buildout.environ.egg-info/entry_points.txt
src/buildout.environ.egg-info/namespace_packages.txt
src/buildout.environ.egg-info/not-zip-safe
src/buildout.environ.egg-info/requires.txt
src/buildout.environ.egg-info/top_level.txt
src/buildout/environ/__init__.py
src/buildout/environ/extension.py