Metadata-Version: 1.1
Name: buildout.environ
Version: 1.1.1
Summary: Expose system environment into buildout section
Home-page: https://pypi.python.org/pypi/buildout.environ
Author: Jens W. Klein
Author-email: jk@kleinundpartner.at
License: GNU General Public License v2 (GPLv2)
Keywords: Python Buildout Extension
Platform: UNKNOWN
Classifier: Intended Audience :: Developers
Classifier: License :: OSI Approved :: Zope Public License
Classifier: Operating System :: OS Independent
Classifier: Programming Language :: Python
Classifier: Programming Language :: Python :: 2.7
Classifier: Programming Language :: Python :: 3.6
Classifier: Programming Language :: Python :: 3.7
Classifier: Topic :: Software Development :: Build Tools
